happyboss/__init__.py
happyboss/main.py
happyboss/move.py
happyboss/user_input.py
happyboss-0.1.0.dist-info/LICENSE
happyboss-0.1.0.dist-info/WHEEL
happyboss-0.1.0.dist-info/METADATA
happyboss-0.1.0.dist-info/RECORD
